k2n_highlights/__init__.py
k2n_highlights/__main__.py
k2n_highlights/bot.py
k2n_highlights/notion/__init__.py
k2n_highlights/notion/cover_search.py
k2n_highlights/notion/formatter.py
k2n_highlights/notion/notion_client.py
k2n_highlights/notion/user_state.py
k2n_highlights/parser/__init__.py
k2n_highlights/parser/html_parser.py
k2n_highlights/utils/__init__.py
k2n_highlights/utils/date.py
k2n_highlights/utils/download.py
k2n_highlights/utils/imgur.py
k2n_highlights-0.2.1.dist-info/licenses/LICENSE
k2n_highlights-0.2.1.dist-info/METADATA
k2n_highlights-0.2.1.dist-info/WHEEL
k2n_highlights-0.2.1.dist-info/entry_points.txt
k2n_highlights-0.2.1.dist-info/top_level.txt
k2n_highlights-0.2.1.dist-info/RECORD
