Metadata-Version: 2.4
Name: k2n-highlights
Version: 0.2.1
Summary: Telegram bot to sync Kindle highlights to Notion
Author: Anton Pokaliukhin
License: LICENSE
Project-URL: Homepage, https://github.com/falone/kindle_highlights_2_notion
Project-URL: Source, https://github.com/falone/kindle_highlights_2_notion
Project-URL: Issues, https://github.com/falone/kindle_highlights_2_notion/issues
Requires-Python: >=3.8
License-File: LICENSE
Requires-Dist: python-telegram-bot==20.0
Requires-Dist: notion-client==2.3.0
Requires-Dist: requests==2.32.3
Requires-Dist: python-dotenv==1.1.0
Requires-Dist: beautifulsoup4==4.13.3
Requires-Dist: lxml==5.3.2
Requires-Dist: httpx==0.23.3
Requires-Dist: yarl==1.19.0
Requires-Dist: multidict==6.4.3
Requires-Dist: attrs==25.3.0
Dynamic: license-file
